cyantic/__init__.py
cyantic/context.py
cyantic/core.py
cyantic/hooks.py
cyantic-0.3.0.dist-info/METADATA
cyantic-0.3.0.dist-info/WHEEL
cyantic-0.3.0.dist-info/licenses/LICENSE
cyantic-0.3.0.dist-info/RECORD
