Metadata-Version: 2.4
Name: cyantic
Version: 0.3.0
Summary: Use Pydantic to build complex types from simple parameters.
Project-URL: Homepage, https://github.com/flywhl/cyantic
Project-URL: Repository, https://github.com/flywhl/cyantic
Project-URL: Documentation, https://github.com/flywhl/cyantic#readme
Project-URL: Bug Tracker, https://github.com/flywhl/cyantic/issues
Author-email: Rory Byrne <rory@rory.bio>
License-Expression: Apache-2.0
License-File: LICENSE
Classifier: Development Status :: 3 - Alpha
Classifier: Intended Audience :: Developers
Classifier: Intended Audience :: Information Technology
Classifier: License :: OSI Approved :: Apache Software License
Classifier: Operating System :: OS Independent
Classifier: Programming Language :: Python
Classifier: Programming Language :: Python :: 3
Classifier: Programming Language :: Python :: 3.9
Classifier: Programming Language :: Python :: 3.10
Classifier: Programming Language :: Python :: 3.11
Classifier: Programming Language :: Python :: 3.12
Classifier: Topic :: Scientific/Engineering
Classifier: Topic :: Software Development :: Libraries :: Python Modules
Classifier: Typing :: Typed
Requires-Python: >=3.9
Requires-Dist: pydantic>=2.10.3
